README.txt
setup.py
stu.py
stu.egg-info/PKG-INFO
stu.egg-info/SOURCES.txt
stu.egg-info/dependency_links.txt
stu.egg-info/entry_points.txt
stu.egg-info/requires.txt
stu.egg-info/top_level.txt