Metadata-Version: 1.0
Name: stu
Version: 1.1
Summary: A simple python template creator.
Home-page: UNKNOWN
Author: Jose Luis Naranjo Gomez
Author-email: luisnaranjo733@hotmail.com
License: GNU GPLv3
Keywords: stu quick python script creator with personalized message
Platform: UNKNOWN
Classifier: License :: OSI Approved :: GNU General Public License (GPL)
Classifier: Topic :: Utilities
